kernelmaker/__init__.py
kernelmaker/__main__.py
kernelmaker-1.1.3.dist-info/LICENSE
kernelmaker-1.1.3.dist-info/METADATA
kernelmaker-1.1.3.dist-info/WHEEL
kernelmaker-1.1.3.dist-info/top_level.txt
kernelmaker-1.1.3.dist-info/RECORD
