Metadata-Version: 2.1
Name: kernelmaker
Version: 1.1.3
Summary: Automate and ease building and configuring mainline kernels
Author-email: Calico Kalamari <author@example.com>
Project-URL: Homepage, https://github.com/Kalamuwu/kernelmaker
Project-URL: Issues, https://github.com/Kalamuwu/kernelmaker/issues
Classifier: Programming Language :: Python :: 3
Classifier: License :: OSI Approved :: MIT License
Classifier: Development Status :: 4 - Beta
Classifier: Intended Audience :: Developers
Classifier: Operating System :: POSIX :: Linux
Classifier: Topic :: System :: Operating System Kernels :: Linux
Requires-Python: >=3.8
License-File: LICENSE
